biswebpython/__init__.py
biswebpython/biswebpy.py
biswebpython/requirements.txt
biswebpython/test_module.py
biswebpython/core/__init__.py
biswebpython/core/bis_basemodule.py
biswebpython/core/bis_baseutils.py
biswebpython/core/bis_commandline.py
biswebpython/core/bis_objects.py
biswebpython/core/bis_wasmutils.py
biswebpython/lib/__init__.py
biswebpython/lib/bismodules_desc.py
biswebpython/lib/biswrapper.py
biswebpython/lib/libbiswasm.so
biswebpython/modules/PythonModuleList.txt
biswebpython/modules/__init__.py
biswebpython/modules/approximateField.py
biswebpython/modules/blankImage.py
biswebpython/modules/butterworthFilter.py
biswebpython/modules/butterworthFilterImage.py
biswebpython/modules/calciumPreprocess.py
biswebpython/modules/clusterThreshold.py
biswebpython/modules/computeCorrelation.py
biswebpython/modules/computeGLM.py
biswebpython/modules/computeROI.py
biswebpython/modules/cropImage.py
biswebpython/modules/displacementField.py
biswebpython/modules/driftCorrectImage.py
biswebpython/modules/extractFrame.py
biswebpython/modules/extractSlice.py
biswebpython/modules/flipImage.py
biswebpython/modules/flipSurface.py
biswebpython/modules/gradientImage.py
biswebpython/modules/individualizedParcellation.py
biswebpython/modules/linearRegistration.py
biswebpython/modules/nonlinearRegistration.py
biswebpython/modules/normalizeImage.py
biswebpython/modules/prepareRegistration.py
biswebpython/modules/regressGlobal.py
biswebpython/modules/regressOut.py
biswebpython/modules/regressOutImage.py
biswebpython/modules/regressionTests.py
biswebpython/modules/regularizeObjectmap.py
biswebpython/modules/resampleImage.py
biswebpython/modules/resliceImage.py
biswebpython/modules/seedCorrelation.py
biswebpython/modules/segmentImage.py
biswebpython/modules/sliceBiasCorrect.py
biswebpython/modules/smoothImage.py
biswebpython/modules/thresholdImage.py
biswebpython/utilities/__init__.py
biswebpython/utilities/calcium_analysis.py
biswebpython-1.1.0b7.dist-info/METADATA
biswebpython-1.1.0b7.dist-info/RECORD
biswebpython-1.1.0b7.dist-info/WHEEL
biswebpython-1.1.0b7.dist-info/entry_points.txt
biswebpython-1.1.0b7.dist-info/top_level.txt
