Metadata-Version: 2.1
Name: biswebpython
Version: 1.1.0b7
Summary: A Medical Image Analysis Package
Home-page: https://github.com/bioimagesuiteweb/bisweb
Author: BioImageSuite Web Team
Author-email: xenophon.papademetris@yale.edu
License: License :: OSI Approved :: GNU General Public License v2 (GPLv2)
Platform: UNKNOWN
Classifier: Programming Language :: Python :: 3.5
Classifier: Operating System :: OS Independent
Requires-Python: >=3.5
Requires-Dist: nibabel
Requires-Dist: numpy
Requires-Dist: pillow
Requires-Dist: scikit-image
Requires-Dist: scikit-learn
Requires-Dist: scipy
Requires-Dist: setuptools
Requires-Dist: wheel (>=0.31)
Requires-Dist: wget
